FastSpellChecker/_backend.cpython-36m-x86_64-linux-gnu.so
FastSpellChecker/Dictionary.py
FastSpellChecker/__init__.py
fastspellchecker-0.0.4.dist-info/WHEEL
fastspellchecker-0.0.4.dist-info/top_level.txt
fastspellchecker-0.0.4.dist-info/RECORD
fastspellchecker-0.0.4.dist-info/LICENSE
fastspellchecker-0.0.4.dist-info/METADATA
